LICENSE
MANIFEST.in
README.md
setup.py
aufmachen/BeautifulSoup.py
aufmachen/BeautifulSoup.pyc
aufmachen/__init__.py
aufmachen/__init__.pyc
aufmachen/crawler.py
aufmachen/crawler.pyc
aufmachen/retrieve.js
aufmachen/server.py
aufmachen/soupselect.py
aufmachen/soupselect.pyc
aufmachen.egg-info/PKG-INFO
aufmachen.egg-info/SOURCES.txt
aufmachen.egg-info/dependency_links.txt
aufmachen.egg-info/top_level.txt
aufmachen/websites/.DS_Store
aufmachen/websites/__init__.py
aufmachen/websites/__init__.pyc
aufmachen/websites/epguides.py
aufmachen/websites/epguides.pyc
aufmachen/websites/immoweb.py
aufmachen/websites/immoweb.pyc
aufmachen/websites/last_fm.py