Metadata-Version: 1.0
Name: aufmachen
Version: 0.2
Summary: Turns a website's HTML into nice, clean objects.
Home-page: http://github.com/fdb/aufmachen
Author: Frederik & Jan De Bleser
Author-email: UNKNOWN
License: BSD
Platform: any
Classifier: Development Status :: 4 - Beta
Classifier: Environment :: Web Environment
Classifier: Intended Audience :: Developers
Classifier: License :: OSI Approved :: BSD License
Classifier: Operating System :: OS Independent
Classifier: Programming Language :: Python
Classifier: Topic :: Internet :: WWW/HTTP :: Dynamic Content
Classifier: Topic :: Software Development :: Libraries :: Python Modules
